[
  {
    "Id": 1,
    "UserName": "churchstout@malathion.com",
    "Name": "Mcdaniel England",
    "DonorType": "Party Plot",
    "VolunteerType": "Individual",
    "AddressLine1": "Senator Street",
    "AddressLine2": "Dictum Court",
    "City": "Matheny",
    "Pincode": 621745,
    "PhoneNumber": "(808) 469-3243",
    "PhotoUrl": "https://randomuser.me/api/portraits/women/1.jpg"
  },
  {
    "Id": 2,
    "UserName": "mcdanielengland@malathion.com",
    "Name": "Mccray Joyner",
    "DonorType": "Hotel",
    "VolunteerType": "Organization",
    "AddressLine1": "Wallabout Street",
    "AddressLine2": "Legion Street",
    "City": "Balm",
    "Pincode": 898173,
    "PhoneNumber": "(851) 468-3119",
    "PhotoUrl": "https://randomuser.me/api/portraits/women/2.jpg"
  },
  {
    "Id": 3,
    "UserName": "mccrayjoyner@malathion.com",
    "Name": "Dixie Beard",
    "DonorType": "Individual",
    "VolunteerType": "Organization",
    "AddressLine1": "Herkimer Court",
    "AddressLine2": "Highland Boulevard",
    "City": "Darlington",
    "Pincode": 819314,
    "PhoneNumber": "(803) 461-3520",
    "PhotoUrl": "https://randomuser.me/api/portraits/women/3.jpg"
  },
  {
    "Id": 4,
    "UserName": "dixiebeard@malathion.com",
    "Name": "Marisol Griffin",
    "DonorType": "Hotel",
    "VolunteerType": "Organization",
    "AddressLine1": "Doughty Street",
    "AddressLine2": "Union Street",
    "City": "Stockdale",
    "Pincode": 647868,
    "PhoneNumber": "(941) 526-2857",
    "PhotoUrl": "https://randomuser.me/api/portraits/women/4.jpg"
  },
  {
    "Id": 5,
    "UserName": "marisolgriffin@malathion.com",
    "Name": "Jean Levy",
    "DonorType": "Party Plot",
    "VolunteerType": "Individual",
    "AddressLine1": "Roebling Street",
    "AddressLine2": "Bergen Place",
    "City": "Blackgum",
    "Pincode": 232067,
    "PhoneNumber": "(994) 418-3771",
    "PhotoUrl": "https://randomuser.me/api/portraits/women/5.jpg"
  },
  {
    "Id": 6,
    "UserName": "janislawrence@malathion.com",
    "Name": "Sherri Mcintyre",
    "DonorType": "Individual",
    "VolunteerType": "Organization",
    "AddressLine1": "Dodworth Street",
    "AddressLine2": "Albany Avenue",
    "City": "Cetronia",
    "Pincode": 565733,
    "PhoneNumber": "(886) 455-3849",
    "PhotoUrl": "https://randomuser.me/api/portraits/men/6.jpg"
  },
  {
    "Id": 7,
    "UserName": "sherrimcintyre@malathion.com",
    "Name": "Hamilton Marshall",
    "DonorType": "Individual",
    "VolunteerType": "Organization",
    "AddressLine1": "Quincy Street",
    "AddressLine2": "Lynch Street",
    "City": "Onton",
    "Pincode": 698686,
    "PhoneNumber": "(862) 418-3594",
    "PhotoUrl": "https://randomuser.me/api/portraits/men/7.jpg"
  },
  {
    "Id": 8,
    "UserName": "hamiltonmarshall@malathion.com",
    "Name": "Barnett Sheppard",
    "DonorType": "Individual",
    "VolunteerType": "Organization",
    "AddressLine1": "Dearborn Court",
    "AddressLine2": "Jackson Place",
    "City": "Taycheedah",
    "Pincode": 633806,
    "PhoneNumber": "(814) 534-3654",
    "PhotoUrl": "https://randomuser.me/api/portraits/men/8.jpg"
  },
  {
    "Id": 9,
    "UserName": "barnettsheppard@malathion.com",
    "Name": "Earnestine Lewis",
    "DonorType": "Party Plot",
    "VolunteerType": "Organization",
    "AddressLine1": "Elmwood Avenue",
    "AddressLine2": "Legion Street",
    "City": "Kimmell",
    "Pincode": 331684,
    "PhoneNumber": "(807) 440-2720",
    "PhotoUrl": "https://randomuser.me/api/portraits/men/9.jpg"
  },
  {
    "Id": 10,
    "UserName": "earnestinelewis@malathion.com",
    "Name": "Weeks Cabrera",
    "DonorType": "Party Plot",
    "VolunteerType": "Individual",
    "AddressLine1": "Sands Street",
    "AddressLine2": "Montague Terrace",
    "City": "Riceville",
    "Pincode": 758977,
    "PhoneNumber": "(991) 509-3281",
    "PhotoUrl": "https://randomuser.me/api/portraits/men/10.jpg"
  }
]